julearn/__init__.py
julearn/_version.py
julearn/api.py
julearn/config.py
julearn/conftest.py
julearn/prepare.py
julearn/base/__init__.py
julearn/base/column_types.py
julearn/base/estimators.py
julearn/base/tests/test_base_estimators.py
julearn/base/tests/test_column_types.py
julearn/external/optuna_searchcv.py
julearn/inspect/__init__.py
julearn/inspect/_cv.py
julearn/inspect/_pipeline.py
julearn/inspect/_preprocess.py
julearn/inspect/inspector.py
julearn/inspect/tests/test_cv.py
julearn/inspect/tests/test_inspector.py
julearn/inspect/tests/test_pipeline.py
julearn/inspect/tests/test_preprocess.py
julearn/model_selection/__init__.py
julearn/model_selection/_optuna_searcher.py
julearn/model_selection/_skopt_searcher.py
julearn/model_selection/available_searchers.py
julearn/model_selection/continuous_stratified_kfold.py
julearn/model_selection/final_model_cv.py
julearn/model_selection/stratified_bootstrap.py
julearn/model_selection/utils.py
julearn/model_selection/tests/test_available_searchers.py
julearn/model_selection/tests/test_continous_stratified_kfold.py
julearn/model_selection/tests/test_final_model_cv.py
julearn/model_selection/tests/test_optuna_searcher.py
julearn/model_selection/tests/test_skopt_searcher.py
julearn/model_selection/tests/test_stratified_bootstrap.py
julearn/models/__init__.py
julearn/models/available_models.py
julearn/models/dynamic.py
julearn/models/tests/test_available_models.py
julearn/models/tests/test_dynamic.py
julearn/models/tests/test_models.py
julearn/pipeline/__init__.py
julearn/pipeline/merger.py
julearn/pipeline/pipeline_creator.py
julearn/pipeline/target_pipeline.py
julearn/pipeline/target_pipeline_creator.py
julearn/pipeline/tests/test_merger.py
julearn/pipeline/tests/test_pipeline_creator.py
julearn/pipeline/tests/test_target_pipeline.py
julearn/pipeline/tests/test_target_pipeline_creator.py
julearn/scoring/__init__.py
julearn/scoring/available_scorers.py
julearn/scoring/metrics.py
julearn-0.3.4.dist-info/AUTHORS.rst
julearn-0.3.4.dist-info/LICENSE.md
julearn-0.3.4.dist-info/METADATA
julearn-0.3.4.dist-info/WHEEL
julearn-0.3.4.dist-info/top_level.txt
julearn-0.3.4.dist-info/RECORD
