Metadata-Version: 2.1
Name: julearn
Version: 0.3.4
Summary: Juelich Machine Learning Library
Author-email: Fede Raimondo <f.raimondo@fz-juelich.de>, Sami Hamdan <s.hamdan@fz-juelich.de>
Maintainer-email: Sami Hamdan <s.hamdan@fz-juelich.de>
License: AGPL-3.0-only
Project-URL: homepage, https://juaml.github.io/julearn
Project-URL: documentation, https://juaml.github.io/julearn
Project-URL: repository, https://github.com/juaml/julearn
Keywords: machine-learning
Classifier: Development Status :: 5 - Production/Stable
Classifier: Intended Audience :: Science/Research
Classifier: Intended Audience :: Developers
Classifier: License :: OSI Approved
Classifier: Natural Language :: English
Classifier: Topic :: Software Development
Classifier: Topic :: Scientific/Engineering
Classifier: Operating System :: OS Independent
Classifier: Programming Language :: Python :: 3.8
Classifier: Programming Language :: Python :: 3.9
Classifier: Programming Language :: Python :: 3.10
Classifier: Programming Language :: Python :: 3.11
Requires-Python: >=3.8
License-File: LICENSE.md
License-File: AUTHORS.rst
Requires-Dist: numpy<1.27,>=1.24
Requires-Dist: pandas<2.3,>=1.5.0
Requires-Dist: statsmodels<0.15,>=0.13
Requires-Dist: scikit-learn<1.6.0,>=1.2.0
Provides-Extra: all
Requires-Dist: julearn[optuna,skopt,viz]; extra == "all"
Provides-Extra: deslib
Requires-Dist: deslib<0.4,>=0.3.5; extra == "deslib"
Provides-Extra: dev
Requires-Dist: tox; extra == "dev"
Requires-Dist: pre-commit; extra == "dev"
Provides-Extra: docs
Requires-Dist: seaborn<0.13,>=0.12.2; extra == "docs"
Requires-Dist: sphinx<7.3,>=5.3.0; extra == "docs"
Requires-Dist: sphinx-gallery<0.15,>=0.13.0; extra == "docs"
Requires-Dist: furo<2024.0.0,>=2022.9.29; extra == "docs"
Requires-Dist: sphinx-copybutton<0.6,>=0.5.0; extra == "docs"
Requires-Dist: numpydoc<1.6,>=1.5.0; extra == "docs"
Requires-Dist: towncrier<24; extra == "docs"
Requires-Dist: scikit-optimize<0.11,>=0.10.0; extra == "docs"
Requires-Dist: optuna<3.7,>=3.6.0; extra == "docs"
Requires-Dist: optuna-integration<4.1,>=3.6.0; extra == "docs"
Provides-Extra: optuna
Requires-Dist: optuna<3.7,>=3.6.0; extra == "optuna"
Requires-Dist: optuna-integration<4.1,>=3.6.0; extra == "optuna"
Provides-Extra: skopt
Requires-Dist: scikit-optimize<0.11,>=0.10.0; extra == "skopt"
Provides-Extra: viz
Requires-Dist: panel>=1.3.0; extra == "viz"
Requires-Dist: bokeh>=3.0.0; extra == "viz"
Requires-Dist: param>=2.0.0; extra == "viz"
